bigquery_advanced_utils/__init__.py
bigquery_advanced_utils/__version__.py
bigquery_advanced_utils/bigquery/__init__.py
bigquery_advanced_utils/bigquery/bigquery.py
bigquery_advanced_utils/core/__init__.py
bigquery_advanced_utils/core/constants.py
bigquery_advanced_utils/core/decorators.py
bigquery_advanced_utils/core/logging_config.py
bigquery_advanced_utils/core/singleton_base.py
bigquery_advanced_utils/datatransfer/__init__.py
bigquery_advanced_utils/datatransfer/datatransfer.py
bigquery_advanced_utils/datatransfer/extended_transfer_config.py
bigquery_advanced_utils/logging/__init__.py
bigquery_advanced_utils/logging/logging.py
bigquery_advanced_utils/storage/__init__.py
bigquery_advanced_utils/storage/storage.py
bigquery_advanced_utils/utils/__init__.py
bigquery_advanced_utils/utils/data_checks.py
bigquery_advanced_utils/utils/exceptions.py
bigquery_advanced_utils/utils/numeric_utils.py
bigquery_advanced_utils/utils/string_utils.py
bigquery_advanced_utils-0.0.1.dev5.dist-info/LICENSE
bigquery_advanced_utils-0.0.1.dev5.dist-info/METADATA
bigquery_advanced_utils-0.0.1.dev5.dist-info/WHEEL
bigquery_advanced_utils-0.0.1.dev5.dist-info/top_level.txt
bigquery_advanced_utils-0.0.1.dev5.dist-info/RECORD
