Metadata-Version: 2.1
Name: bigquery-advanced-utils
Version: 0.0.1.dev5
Summary: A utility library that enhances the official BigQuery Python client by providing additional tools for efficient query management, data processing, and automation. Designed for developers and data scientists, `bigquery-advanced-utils` simplifies working with Google BigQuery.
Author-email: Alessio Siciliano <alessiosiciliano@outlook.it>
License: GPL-3.0
Keywords: python,bigquery,google-cloud,datatransfer
Classifier: Programming Language :: Python :: 3
Classifier: Intended Audience :: Developers
Classifier: Operating System :: OS Independent
Requires-Python: >=3.10
License-File: LICENSE
Requires-Dist: google-cloud-bigquery-datatransfer==3.17.1
Requires-Dist: google-cloud-resource-manager==1.13.1
Requires-Dist: google-cloud-bigquery==3.27.0
Requires-Dist: google-cloud-logging==3.11.3
Requires-Dist: google-cloud-storage==2.19.0
Requires-Dist: types-requests==2.32.0.20241016
